openfilectl/__init__.py
openfilectl/__main__.py
openfilectl/cli.py
pyopenfilectl-0.0.1.dist-info/METADATA
pyopenfilectl-0.0.1.dist-info/WHEEL
pyopenfilectl-0.0.1.dist-info/entry_points.txt
pyopenfilectl-0.0.1.dist-info/top_level.txt
pyopenfilectl-0.0.1.dist-info/RECORD
