Metadata-Version: 2.1
Name: pyopenfilectl
Version: 0.0.1
Summary: UNKNOWN
Home-page: UNKNOWN
Author: greene
License: UNKNOWN
Platform: UNKNOWN
Requires-Python: >=3.8
Requires-Dist: httpx
Requires-Dist: aiofiles
Requires-Dist: click
Requires-Dist: tqdm
Provides-Extra: dev
Requires-Dist: black ; extra == 'dev'
Requires-Dist: pytest ; extra == 'dev'
Requires-Dist: pip-tools ; extra == 'dev'
